anonymizer/__init__.py
anonymizer/anonymizer.py
tdf-anonymizer/__init__.py
tdf-anonymizer/anonymizer.py
tdf-anonymizer/tdf-anonymizer.py
tdf_anonymizer-0.4.dist-info/METADATA
tdf_anonymizer-0.4.dist-info/WHEEL
tdf_anonymizer-0.4.dist-info/top_level.txt
tdf_anonymizer-0.4.dist-info/RECORD
