Metadata-Version: 2.1
Name: tdf-anonymizer
Version: 0.4
Requires-Dist: nltk
Requires-Dist: pydantic
Requires-Dist: faker
Requires-Dist: pandas
